<annotation>
	<folder>五代花鸟画派</folder>
	<filename>gra20.jpg</filename>
	<path>D:\迁移学习\五代花鸟画派\gra20.jpg</path>
	<source>
		<database>Unknown</database>
	</source>
	<size>
		<width>900</width>
		<height>1927</height>
		<depth>3</depth>
	</size>
	<segmented>0</segmented>
	<object>
		<name>crane</name>
		<pose>Unspecified</pose>
		<truncated>0</truncated>
		<difficult>0</difficult>
		<bndbox>
			<xmin>333</xmin>
			<ymin>641</ymin>
			<xmax>787</xmax>
			<ymax>1289</ymax>
		</bndbox>
	</object>
	<object>
		<name>tree</name>
		<pose>Unspecified</pose>
		<truncated>1</truncated>
		<difficult>0</difficult>
		<bndbox>
			<xmin>3</xmin>
			<ymin>9</ymin>
			<xmax>900</xmax>
			<ymax>1569</ymax>
		</bndbox>
	</object>
	<object>
		<name>flower</name>
		<pose>Unspecified</pose>
		<truncated>1</truncated>
		<difficult>0</difficult>
		<bndbox>
			<xmin>1</xmin>
			<ymin>1225</ymin>
			<xmax>537</xmax>
			<ymax>1365</ymax>
		</bndbox>
	</object>
</annotation>
