<annotation>
	<folder>元四家</folder>
	<filename>d52a2834349b033b173bc09d15ce36d3d439bdc1.webp</filename>
	<path>/Users/yuuekiketa/Downloads/元四家/d52a2834349b033b173bc09d15ce36d3d439bdc1.webp</path>
	<source>
		<database>Unknown</database>
	</source>
	<size>
		<width>525</width>
		<height>1279</height>
		<depth>3</depth>
	</size>
	<segmented>0</segmented>
	<object>
		<name>tree</name>
		<pose>Unspecified</pose>
		<truncated>0</truncated>
		<difficult>0</difficult>
		<bndbox>
			<xmin>55</xmin>
			<ymin>501</ymin>
			<xmax>304</xmax>
			<ymax>1135</ymax>
		</bndbox>
	</object>
	<object>
		<name>bamboo</name>
		<pose>Unspecified</pose>
		<truncated>0</truncated>
		<difficult>0</difficult>
		<bndbox>
			<xmin>79</xmin>
			<ymin>931</ymin>
			<xmax>163</xmax>
			<ymax>1135</ymax>
		</bndbox>
	</object>
	<object>
		<name>rock</name>
		<pose>Unspecified</pose>
		<truncated>0</truncated>
		<difficult>0</difficult>
		<bndbox>
			<xmin>258</xmin>
			<ymin>931</ymin>
			<xmax>471</xmax>
			<ymax>1160</ymax>
		</bndbox>
	</object>
</annotation>
