<annotation>
	<folder>南宋四家</folder>
	<filename>ac4bd11373f08202913680414bfbfbedab641b23.jpg</filename>
	<path>D:\朱妍\艺术小样本\南宋四家\ac4bd11373f08202913680414bfbfbedab641b23.jpg</path>
	<source>
		<database>Unknown</database>
	</source>
	<size>
		<width>450</width>
		<height>406</height>
		<depth>3</depth>
	</size>
	<segmented>0</segmented>
	<object>
		<name>man</name>
		<pose>Unspecified</pose>
		<truncated>0</truncated>
		<difficult>0</difficult>
		<bndbox>
			<xmin>335</xmin>
			<ymin>211</ymin>
			<xmax>414</xmax>
			<ymax>355</ymax>
		</bndbox>
	</object>
	<object>
		<name>man</name>
		<pose>Unspecified</pose>
		<truncated>0</truncated>
		<difficult>0</difficult>
		<bndbox>
			<xmin>208</xmin>
			<ymin>171</ymin>
			<xmax>322</xmax>
			<ymax>332</ymax>
		</bndbox>
	</object>
	<object>
		<name>man</name>
		<pose>Unspecified</pose>
		<truncated>0</truncated>
		<difficult>0</difficult>
		<bndbox>
			<xmin>119</xmin>
			<ymin>203</ymin>
			<xmax>231</xmax>
			<ymax>330</ymax>
		</bndbox>
	</object>
	<object>
		<name>man</name>
		<pose>Unspecified</pose>
		<truncated>0</truncated>
		<difficult>0</difficult>
		<bndbox>
			<xmin>31</xmin>
			<ymin>168</ymin>
			<xmax>118</xmax>
			<ymax>297</ymax>
		</bndbox>
	</object>
	<object>
		<name>woman</name>
		<pose>Unspecified</pose>
		<truncated>0</truncated>
		<difficult>0</difficult>
		<bndbox>
			<xmin>18</xmin>
			<ymin>181</ymin>
			<xmax>135</xmax>
			<ymax>289</ymax>
		</bndbox>
	</object>
	<object>
		<name>woman</name>
		<pose>Unspecified</pose>
		<truncated>0</truncated>
		<difficult>0</difficult>
		<bndbox>
			<xmin>144</xmin>
			<ymin>139</ymin>
			<xmax>219</xmax>
			<ymax>233</ymax>
		</bndbox>
	</object>
	<object>
		<name>tree</name>
		<pose>Unspecified</pose>
		<truncated>1</truncated>
		<difficult>0</difficult>
		<bndbox>
			<xmin>3</xmin>
			<ymin>1</ymin>
			<xmax>330</xmax>
			<ymax>124</ymax>
		</bndbox>
	</object>
</annotation>
